{
  "station": "9410660",
  "station_name": "Los Angeles (Outer Harbor), CA",
  "updated_at": "2026-05-03T03:35:42.644579+00:00",
  "datum": "MLLW",
  "units": "ft",
  "predictions": [
    {
      "t": "2026-05-03 04:55",
      "v": "5.674",
      "type": "H"
    },
    {
      "t": "2026-05-03 12:12",
      "v": "-0.468",
      "type": "L"
    },
    {
      "t": "2026-05-03 18:41",
      "v": "3.327",
      "type": "H"
    },
    {
      "t": "2026-05-03 22:59",
      "v": "2.204",
      "type": "L"
    },
    {
      "t": "2026-05-04 05:21",
      "v": "5.523",
      "type": "H"
    },
    {
      "t": "2026-05-04 12:51",
      "v": "-0.303",
      "type": "L"
    },
    {
      "t": "2026-05-04 19:31",
      "v": "3.114",
      "type": "H"
    },
    {
      "t": "2026-05-04 23:21",
      "v": "2.443",
      "type": "L"
    },
    {
      "t": "2026-05-05 05:51",
      "v": "5.305",
      "type": "H"
    },
    {
      "t": "2026-05-05 13:36",
      "v": "-0.077",
      "type": "L"
    },
    {
      "t": "2026-05-05 20:36",
      "v": "2.948",
      "type": "H"
    },
    {
      "t": "2026-05-05 23:41",
      "v": "2.668",
      "type": "L"
    },
    {
      "t": "2026-05-06 06:24",
      "v": "5.032",
      "type": "H"
    },
    {
      "t": "2026-05-06 14:28",
      "v": "0.157",
      "type": "L"
    },
    {
      "t": "2026-05-07 07:05",
      "v": "4.715",
      "type": "H"
    },
    {
      "t": "2026-05-07 15:30",
      "v": "0.339",
      "type": "L"
    },
    {
      "t": "2026-05-08 08:01",
      "v": "4.371",
      "type": "H"
    },
    {
      "t": "2026-05-08 16:35",
      "v": "0.434",
      "type": "L"
    },
    {
      "t": "2026-05-09 00:51",
      "v": "3.372",
      "type": "H"
    },
    {
      "t": "2026-05-09 03:45",
      "v": "3.24",
      "type": "L"
    },
    {
      "t": "2026-05-09 09:25",
      "v": "4.056",
      "type": "H"
    },
    {
      "t": "2026-05-09 17:32",
      "v": "0.466",
      "type": "L"
    },
    {
      "t": "2026-05-10 01:04",
      "v": "3.683",
      "type": "H"
    },
    {
      "t": "2026-05-10 05:51",
      "v": "2.886",
      "type": "L"
    },
    {
      "t": "2026-05-10 11:01",
      "v": "3.882",
      "type": "H"
    },
    {
      "t": "2026-05-10 18:19",
      "v": "0.498",
      "type": "L"
    }
  ]
}